plonetheme.future_imperfect-1.0a1-py2.7-nspkg.pth
plonetheme/future_imperfect/__init__.py
plonetheme/future_imperfect/configure.zcml
plonetheme/future_imperfect/interfaces.py
plonetheme/future_imperfect/setuphandlers.py
plonetheme/future_imperfect/testing.py
plonetheme/future_imperfect/browser/__init__.py
plonetheme/future_imperfect/browser/configure.zcml
plonetheme/future_imperfect/browser/overrides/.gitkeep
plonetheme/future_imperfect/browser/static/.gitkeep
plonetheme/future_imperfect/locales/plonetheme.future_imperfect.pot
plonetheme/future_imperfect/locales/update.sh
plonetheme/future_imperfect/profiles/default/browserlayer.xml
plonetheme/future_imperfect/profiles/default/metadata.xml
plonetheme/future_imperfect/profiles/default/theme.xml
plonetheme/future_imperfect/profiles/uninstall/browserlayer.xml
plonetheme/future_imperfect/profiles/uninstall/theme.xml
plonetheme/future_imperfect/tests/__init__.py
plonetheme/future_imperfect/tests/test_robot.py
plonetheme/future_imperfect/tests/test_setup.py
plonetheme/future_imperfect/tests/robot/test_example.robot
plonetheme/future_imperfect/theme/LICENSE.txt
plonetheme/future_imperfect/theme/README.txt
plonetheme/future_imperfect/theme/index.html
plonetheme/future_imperfect/theme/manifest.cfg
plonetheme/future_imperfect/theme/preview.png
plonetheme/future_imperfect/theme/rules.xml
plonetheme/future_imperfect/theme/fonts/FontAwesome.otf
plonetheme/future_imperfect/theme/fonts/fontawesome-webfont.eot
plonetheme/future_imperfect/theme/fonts/fontawesome-webfont.svg
plonetheme/future_imperfect/theme/fonts/fontawesome-webfont.ttf
plonetheme/future_imperfect/theme/fonts/fontawesome-webfont.woff
plonetheme/future_imperfect/theme/fonts/fontawesome-webfont.woff2
plonetheme/future_imperfect/theme/less/default.css
plonetheme/future_imperfect/theme/less/font-awesome.min.css
plonetheme/future_imperfect/theme/less/future_imperfect-compiled.css.map
plonetheme/future_imperfect/theme/less/main.less
plonetheme.future_imperfect-1.0a1.dist-info/DESCRIPTION.rst
plonetheme.future_imperfect-1.0a1.dist-info/METADATA
plonetheme.future_imperfect-1.0a1.dist-info/RECORD
plonetheme.future_imperfect-1.0a1.dist-info/WHEEL
plonetheme.future_imperfect-1.0a1.dist-info/entry_points.txt
plonetheme.future_imperfect-1.0a1.dist-info/metadata.json
plonetheme.future_imperfect-1.0a1.dist-info/namespace_packages.txt
plonetheme.future_imperfect-1.0a1.dist-info/top_level.txt
