Metadata-Version: 2.0
Name: plonetheme.future-imperfect
Version: 1.0a1
Summary: A theme for Plone 5
Home-page: https://github.com/vikas-parashar/plonetheme.future_imperfect
Author: Vikas Parashar
Author-email: svnitvikas@gmail.com
License: MIT License
Keywords: Python Plone
Platform: UNKNOWN
Classifier: Environment :: Web Environment
Classifier: Framework :: Plone
Classifier: Framework :: Plone :: 5.0
Classifier: Programming Language :: Python
Classifier: Programming Language :: Python :: 2.7
Classifier: Operating System :: OS Independent
Classifier: License :: OSI Approved :: MIT License
Requires-Dist: Products.GenericSetup (>=1.8.2)
Requires-Dist: plone.api
Requires-Dist: plone.app.theming
Requires-Dist: plone.app.themingplugins
Requires-Dist: setuptools
Requires-Dist: z3c.jbot
Provides-Extra: test
Requires-Dist: plone.app.contenttypes; extra == 'test'
Requires-Dist: plone.app.robotframework[debug]; extra == 'test'
Requires-Dist: plone.app.testing; extra == 'test'
Requires-Dist: plone.testing (>=5.0.0); extra == 'test'
